unidec/DataCollector.py
unidec/GUniDec.py
unidec/ImportWizard.py
unidec/Launcher.py
unidec/MetaUniDec.py
unidec/UPP.py
unidec/UniChrom.py
unidec/UniChromCD.py
unidec/UniDecCD.py
unidec/__init__.py
unidec/__main__.py
unidec/batch.py
unidec/engine.py
unidec/tools.py
unidec/IsoDec/IsoDecGUI.py
unidec/IsoDec/__init__.py
unidec/IsoDec/__main__.py
unidec/IsoDec/altdecon.py
unidec/IsoDec/c_interface.py
unidec/IsoDec/datatools.py
unidec/IsoDec/encoding.py
unidec/IsoDec/engine.py
unidec/IsoDec/fftw3.lib
unidec/IsoDec/isodec_test
unidec/IsoDec/isodec_test.exe
unidec/IsoDec/isodeclib.dll
unidec/IsoDec/isodeclib.lib
unidec/IsoDec/isodeclib.so
unidec/IsoDec/isogen.dll
unidec/IsoDec/isogen.lib
unidec/IsoDec/isogen.so
unidec/IsoDec/isogenwrapper.py
unidec/IsoDec/libfftw3.so
unidec/IsoDec/match.py
unidec/IsoDec/models.py
unidec/IsoDec/msalign_export.py
unidec/IsoDec/oldisodecfunctions.py
unidec/IsoDec/phase_model_1.pth
unidec/IsoDec/phase_model_4.pth
unidec/IsoDec/phase_model_8.pth
unidec/IsoDec/plots.py
unidec/IsoDec/runtime.py
unidec/IsoDec/train.py
unidec/IsoDec/trainingdata.py
unidec/IsoDec/ucrtbase.dll
unidec/IsoDec/vcruntime140.dll
unidec/IsoDec/IDGUI/IsoDecControls.py
unidec/IsoDec/IDGUI/IsoDecMenu.py
unidec/IsoDec/IDGUI/IsoDecView.py
unidec/IsoDec/IDGUI/__init__.py
unidec/IsoDec/IsoDec tests/datatoolstest.py
unidec/IsoDec/IsoGen/__init__.py
unidec/IsoDec/IsoGen/isogen_base.py
unidec/IsoDec/IsoGen/isogen_rnaveragine_model128.pth
unidec/IsoDec/IsoGen/isogen_rnaveragine_model32.pth
unidec/IsoDec/IsoGen/isogen_rnaveragine_model64.pth
unidec/IsoDec/IsoGen/isogen_tools.py
unidec/IsoDec/IsoGen/isogenatom.py
unidec/IsoDec/IsoGen/isogenatom_synthetic_training.py
unidec/IsoDec/IsoGen/isogenatom_trainingdata.py
unidec/IsoDec/IsoGen/isogenc.py
unidec/IsoDec/IsoGen/isogenmass.py
unidec/IsoDec/IsoGen/isogenmass_model_1024.pth
unidec/IsoDec/IsoGen/isogenmass_model_128.pth
unidec/IsoDec/IsoGen/isogenmass_model_64.pth
unidec/IsoDec/IsoGen/isogenpep.py
unidec-8.0.3.dist-info/licenses/LICENSE
unidec-8.0.3.dist-info/METADATA
unidec-8.0.3.dist-info/WHEEL
unidec-8.0.3.dist-info/entry_points.txt
unidec-8.0.3.dist-info/top_level.txt
unidec-8.0.3.dist-info/RECORD
