Metadata-Version: 2.4
Name: UniDec
Version: 8.0.3
Summary: Universal Deconvolution of Mass and Ion Mobility Spectra
Home-page: https://github.com/michaelmarty/UniDec
Author: Michael Marty
Author-email: Michael Marty <mtmarty@utexas.edu>
License: UniDec License:
Project-URL: Homepage, https://github.com/michaelmarty/UniDec
Keywords: Mass Spectrometry,Ion Mobility,Deconvolution
Classifier: Programming Language :: Python
Classifier: Programming Language :: Python :: 3
Requires-Python: >=3.7
License-File: LICENSE
Requires-Dist: numpy>=1.16
Requires-Dist: scipy>=1.2
Requires-Dist: matplotlib>=3.7
Requires-Dist: pandas
Requires-Dist: pymzml
Requires-Dist: natsort
Requires-Dist: networkx
Requires-Dist: h5py
Requires-Dist: pypubsub
Requires-Dist: numba
Requires-Dist: pyimzml
Requires-Dist: pythonnet
Requires-Dist: pyteomics
Requires-Dist: lxml
Requires-Dist: lxml_html_clean
Requires-Dist: pywin32
Provides-Extra: dev
Requires-Dist: massql; extra == "dev"
Requires-Dist: pytest; extra == "dev"
Requires-Dist: pyinstaller; extra == "dev"
Requires-Dist: molmass; extra == "dev"
Requires-Dist: mpld3; extra == "dev"
Requires-Dist: wxpython>=4.0; extra == "dev"
Dynamic: author
Dynamic: home-page
Dynamic: license-file
Dynamic: requires-python
